zodbupdate/__init__.py
zodbupdate/convert.py
zodbupdate/main.py
zodbupdate/serialize.py
zodbupdate/tests.py
zodbupdate/update.py
zodbupdate/utils.py
zodbupdate-3.0.dist-info/licenses/LICENSE.txt
zodbupdate-3.0.dist-info/METADATA
zodbupdate-3.0.dist-info/WHEEL
zodbupdate-3.0.dist-info/entry_points.txt
zodbupdate-3.0.dist-info/top_level.txt
zodbupdate-3.0.dist-info/RECORD
