Metadata-Version: 2.4
Name: zodbupdate
Version: 3.0
Summary: Update ZODB class references for moved or renamed classes.
Home-page: https://github.com/zopefoundation/zodbupdate/
Author: Zope Developers
Author-email: zope-dev@zope.dev
License: ZPL-2.1
Keywords: zodb update upgrade migrate data pickle
Classifier: Development Status :: 6 - Mature
Classifier: Framework :: Zope :: 3
Classifier: Framework :: Zope :: 5
Classifier: License :: OSI Approved :: Zope Public License
Classifier: Operating System :: OS Independent
Classifier: Programming Language :: Python
Classifier: Programming Language :: Python :: 3
Classifier: Programming Language :: Python :: 3.9
Classifier: Programming Language :: Python :: 3.10
Classifier: Programming Language :: Python :: 3.11
Classifier: Programming Language :: Python :: 3.12
Classifier: Programming Language :: Python :: 3.13
Classifier: Programming Language :: Python :: Implementation :: CPython
Requires-Python: >=3.9
License-File: LICENSE.txt
Requires-Dist: ZODB
Requires-Dist: transaction
Requires-Dist: zodbpickle
Requires-Dist: importlib-metadata; python_version < "3.10"
Provides-Extra: test
Requires-Dist: persistent; extra == "test"
Requires-Dist: zope.interface; extra == "test"
Requires-Dist: relstorage; extra == "test"
Requires-Dist: six; extra == "test"
Dynamic: author
Dynamic: author-email
Dynamic: classifier
Dynamic: description
Dynamic: home-page
Dynamic: keywords
Dynamic: license
Dynamic: license-file
Dynamic: provides-extra
Dynamic: requires-dist
Dynamic: requires-python
Dynamic: summary
